pylint_fixme_info/__init__.py
pylint_fixme_info-1.0.4.dist-info/LICENSE.txt
pylint_fixme_info-1.0.4.dist-info/METADATA
pylint_fixme_info-1.0.4.dist-info/WHEEL
pylint_fixme_info-1.0.4.dist-info/top_level.txt
pylint_fixme_info-1.0.4.dist-info/RECORD
