Metadata-Version: 2.1
Name: pylint-fixme-info
Version: 1.0.4
Summary: A pylint checker for reporting fixmes with Info level
Home-page: https://github.com/mxmeinhold/pylint-fixme-info
Author: Max Meinhold
Author-email: mxmeinhold@gmail.com
License: MIT
Project-URL: Bug Tracker, https://github.com/mxmeinhold/pylint-fixme-info/issues
Keywords: pylint,linting
Classifier: Programming Language :: Python :: 3
Classifier: License :: OSI Approved :: MIT License
Classifier: Operating System :: OS Independent
Classifier: Natural Language :: English
Classifier: Intended Audience :: Developers
Classifier: Topic :: Software Development
Classifier: Topic :: Utilities
Requires-Python: >=3.7
License-File: LICENSE.txt
Requires-Dist: pylint >=2.14.0
